[
  {
    "id": "AUD1020F2A6",
    "action": "group.create",
    "entityType": "group",
    "entityId": "GRP826401A7",
    "entityName": "sdddsffg",
    "userId": "u001",
    "userName": "Ahmed Al-Rashidi",
    "details": "Created group \"sdddsffg\"",
    "timestamp": "2026-04-07T09:03:09.838Z"
  },
  {
    "id": "AUDFF764473",
    "action": "document.version",
    "entityType": "document",
    "entityId": "DOC1A2B3C04",
    "entityName": "Board Meeting Minutes - March 2026",
    "userId": "u001",
    "userName": "Ahmed Al-Rashidi",
    "details": "Uploaded version 2",
    "timestamp": "2026-04-07T09:15:33.170Z"
  },
  {
    "id": "AUD5D27E3FA",
    "action": "group.delete",
    "entityType": "group",
    "entityId": "GRP826401A7",
    "entityName": "sdddsffg",
    "userId": "u001",
    "userName": "Ahmed Al-Rashidi",
    "details": "Deleted group \"sdddsffg\"",
    "timestamp": "2026-04-07T09:16:42.936Z"
  },
  {
    "id": "AUD0019A72A",
    "action": "group.create",
    "entityType": "group",
    "entityId": "GRP22DAF0F4",
    "entityName": "jgg",
    "userId": "u001",
    "userName": "Ahmed Al-Rashidi",
    "details": "Created group \"jgg\"",
    "timestamp": "2026-04-07T09:17:09.709Z"
  },
  {
    "id": "AUD2D519CBD",
    "action": "group.create",
    "entityType": "group",
    "entityId": "GRP83F665A4",
    "entityName": "jgg",
    "userId": "u001",
    "userName": "Ahmed Al-Rashidi",
    "details": "Created group \"jgg\"",
    "timestamp": "2026-04-07T09:17:09.712Z"
  },
  {
    "id": "AUDF1494DFC",
    "action": "group.create",
    "entityType": "group",
    "entityId": "GRPD83F88EA",
    "entityName": "jgg",
    "userId": "u001",
    "userName": "Ahmed Al-Rashidi",
    "details": "Created group \"jgg\"",
    "timestamp": "2026-04-07T09:17:09.714Z"
  },
  {
    "id": "AUD2C7A5B58",
    "action": "group.create",
    "entityType": "group",
    "entityId": "GRPF116DAB9",
    "entityName": "jgg",
    "userId": "u001",
    "userName": "Ahmed Al-Rashidi",
    "details": "Created group \"jgg\"",
    "timestamp": "2026-04-07T09:17:09.715Z"
  },
  {
    "id": "AUDFBF893EC",
    "action": "group.create",
    "entityType": "group",
    "entityId": "GRP328107CF",
    "entityName": "jgg",
    "userId": "u001",
    "userName": "Ahmed Al-Rashidi",
    "details": "Created group \"jgg\"",
    "timestamp": "2026-04-07T09:17:09.717Z"
  },
  {
    "id": "AUD42CA0E75",
    "action": "group.delete",
    "entityType": "group",
    "entityId": "GRP22DAF0F4",
    "entityName": "jgg",
    "userId": "u001",
    "userName": "Ahmed Al-Rashidi",
    "details": "Deleted group \"jgg\"",
    "timestamp": "2026-04-07T09:17:16.173Z"
  },
  {
    "id": "AUD217F48B6",
    "action": "group.delete",
    "entityType": "group",
    "entityId": "GRP83F665A4",
    "entityName": "jgg",
    "userId": "u001",
    "userName": "Ahmed Al-Rashidi",
    "details": "Deleted group \"jgg\"",
    "timestamp": "2026-04-07T09:17:21.190Z"
  },
  {
    "id": "AUD33D307FF",
    "action": "group.delete",
    "entityType": "group",
    "entityId": "GRPD83F88EA",
    "entityName": "jgg",
    "userId": "u001",
    "userName": "Ahmed Al-Rashidi",
    "details": "Deleted group \"jgg\"",
    "timestamp": "2026-04-07T09:17:22.836Z"
  },
  {
    "id": "AUD99AC07AA",
    "action": "group.delete",
    "entityType": "group",
    "entityId": "GRPF116DAB9",
    "entityName": "jgg",
    "userId": "u001",
    "userName": "Ahmed Al-Rashidi",
    "details": "Deleted group \"jgg\"",
    "timestamp": "2026-04-07T09:17:26.050Z"
  },
  {
    "id": "AUD8F52E344",
    "action": "group.delete",
    "entityType": "group",
    "entityId": "GRP328107CF",
    "entityName": "jgg",
    "userId": "u001",
    "userName": "Ahmed Al-Rashidi",
    "details": "Deleted group \"jgg\"",
    "timestamp": "2026-04-07T09:17:28.172Z"
  },
  {
    "id": "AUD63118405",
    "action": "group.memberAdd",
    "entityType": "group",
    "entityId": "GRP1A2B3C01",
    "entityName": "Finance Team",
    "userId": "u001",
    "userName": "Ahmed Al-Rashidi",
    "details": "Added 1 member(s)",
    "timestamp": "2026-04-07T09:18:32.899Z"
  },
  {
    "id": "AUDBD5BA865",
    "action": "document.upload",
    "entityType": "document",
    "entityId": "DOC3B11FE59",
    "entityName": "dddd",
    "userId": "u001",
    "userName": "Ahmed Al-Rashidi",
    "details": "Created document with file upload",
    "timestamp": "2026-04-07T11:25:37.221Z"
  },
  {
    "id": "AUD2B117809",
    "action": "document.version",
    "entityType": "document",
    "entityId": "DOC1A2B3C04",
    "entityName": "Board Meeting Minutes - March 2026",
    "userId": "u001",
    "userName": "Ahmed Al-Rashidi",
    "details": "Uploaded version 3",
    "timestamp": "2026-04-07T21:39:37.854Z"
  },
  {
    "id": "AUD13441222",
    "action": "document.sign",
    "entityType": "document",
    "entityId": "DOC1A2B3C04",
    "entityName": "Board Meeting Minutes - March 2026",
    "userId": "u001",
    "userName": "Ahmed Al-Rashidi",
    "details": "Applied signature",
    "timestamp": "2026-04-07T21:42:47.029Z"
  },
  {
    "id": "AUD59252587",
    "action": "document.sign",
    "entityType": "document",
    "entityId": "DOC1A2B3C04",
    "entityName": "Board Meeting Minutes - March 2026",
    "userId": "u001",
    "userName": "Ahmed Al-Rashidi",
    "details": "Applied signature",
    "timestamp": "2026-04-07T21:55:53.212Z"
  },
  {
    "id": "AUDA51FA083",
    "action": "document.sign",
    "entityType": "document",
    "entityId": "DOC1A2B3C04",
    "entityName": "Board Meeting Minutes - March 2026",
    "userId": "u001",
    "userName": "Ahmed Al-Rashidi",
    "details": "Applied signature",
    "timestamp": "2026-04-07T22:11:21.167Z"
  },
  {
    "id": "AUDAD06CC86",
    "action": "document.sign",
    "entityType": "document",
    "entityId": "DOC1A2B3C04",
    "entityName": "Board Meeting Minutes - March 2026",
    "userId": "u001",
    "userName": "Ahmed Al-Rashidi",
    "details": "Applied signature",
    "timestamp": "2026-04-07T22:12:08.630Z"
  },
  {
    "id": "AUDACFDA4CC",
    "action": "document.sign",
    "entityType": "document",
    "entityId": "DOC1A2B3C04",
    "entityName": "Board Meeting Minutes - March 2026",
    "userId": "u001",
    "userName": "Ahmed Al-Rashidi",
    "details": "Applied signature",
    "timestamp": "2026-04-07T22:22:26.784Z"
  },
  {
    "id": "AUD2CCED695",
    "action": "document.sign",
    "entityType": "document",
    "entityId": "DOC1A2B3C04",
    "entityName": "Board Meeting Minutes - March 2026",
    "userId": "u001",
    "userName": "Ahmed Al-Rashidi",
    "details": "Applied signature",
    "timestamp": "2026-04-08T09:21:28.418Z"
  },
  {
    "id": "AUDE1812457",
    "action": "document.sign",
    "entityType": "document",
    "entityId": "DOC1A2B3C04",
    "entityName": "Board Meeting Minutes - March 2026",
    "userId": "u001",
    "userName": "Ahmed Al-Rashidi",
    "details": "Applied signature",
    "timestamp": "2026-04-08T09:24:06.616Z"
  },
  {
    "id": "AUD554A0CB7",
    "action": "document.sign",
    "entityType": "document",
    "entityId": "DOC1A2B3C04",
    "entityName": "Board Meeting Minutes - March 2026",
    "userId": "u001",
    "userName": "Ahmed Al-Rashidi",
    "details": "Applied signature",
    "timestamp": "2026-04-08T09:24:22.613Z"
  },
  {
    "id": "AUD5425CF63",
    "action": "document.upload",
    "entityType": "document",
    "entityId": "DOC4041BA18",
    "entityName": "Proposal",
    "userId": "u001",
    "userName": "Ahmed Al-Rashidi",
    "details": "Created document with file upload",
    "timestamp": "2026-04-08T16:21:20.624Z"
  },
  {
    "id": "AUD0DFA2518",
    "action": "document.sign",
    "entityType": "document",
    "entityId": "DOC4041BA18",
    "entityName": "Proposal",
    "userId": "u001",
    "userName": "Ahmed Al-Rashidi",
    "details": "Applied signature",
    "timestamp": "2026-04-08T16:45:25.903Z"
  },
  {
    "id": "AUD46AF9D43",
    "action": "document.sign",
    "entityType": "document",
    "entityId": "DOC4041BA18",
    "entityName": "Proposal",
    "userId": "u001",
    "userName": "Ahmed Al-Rashidi",
    "details": "Applied signature",
    "timestamp": "2026-04-08T16:45:48.360Z"
  },
  {
    "id": "AUD120CC667",
    "action": "document.sign",
    "entityType": "document",
    "entityId": "DOC4041BA18",
    "entityName": "Proposal",
    "userId": "u001",
    "userName": "Ahmed Al-Rashidi",
    "details": "Applied signature",
    "timestamp": "2026-04-08T16:50:25.168Z"
  },
  {
    "id": "AUD37D348A7",
    "action": "document.sign",
    "entityType": "document",
    "entityId": "DOC4041BA18",
    "entityName": "Proposal",
    "userId": "u001",
    "userName": "Ahmed Al-Rashidi",
    "details": "Applied signature",
    "timestamp": "2026-04-08T16:57:48.409Z"
  },
  {
    "id": "AUD4A7EE932",
    "action": "document.sign",
    "entityType": "document",
    "entityId": "DOC4041BA18",
    "entityName": "Proposal",
    "userId": "u001",
    "userName": "Ahmed Al-Rashidi",
    "details": "Applied signature",
    "timestamp": "2026-04-08T17:02:46.007Z"
  },
  {
    "id": "AUD21626F03",
    "action": "document.sign",
    "entityType": "document",
    "entityId": "DOC4041BA18",
    "entityName": "Proposal",
    "userId": "u004",
    "userName": "Sara Hassan",
    "details": "Applied signature",
    "timestamp": "2026-04-12T10:07:20.995Z"
  },
  {
    "id": "AUDA203B11B",
    "action": "document.sign",
    "entityType": "document",
    "entityId": "DOC4041BA18",
    "entityName": "Proposal",
    "userId": "u004",
    "userName": "Sara Hassan",
    "details": "Applied signature",
    "timestamp": "2026-04-12T10:07:21.124Z"
  },
  {
    "id": "AUD83C2B29A",
    "action": "document.upload",
    "entityType": "document",
    "entityId": "DOC604A5DD0",
    "entityName": "Proposal",
    "userId": "u004",
    "userName": "Sara Hassan",
    "details": "Created document with file upload",
    "timestamp": "2026-04-12T10:22:44.324Z"
  },
  {
    "id": "AUDB687A66C",
    "action": "document.sign",
    "entityType": "document",
    "entityId": "DOC604A5DD0",
    "entityName": "Proposal",
    "userId": "u001",
    "userName": "Ahmed Al-Rashidi",
    "details": "Applied signature",
    "timestamp": "2026-04-14T12:41:25.893Z"
  },
  {
    "id": "AUD4C5A7442",
    "action": "document.upload",
    "entityType": "document",
    "entityId": "DOCA5391BC0",
    "entityName": "Saudi Downtown",
    "userId": "u003",
    "userName": "Fatima Al-Zahra",
    "details": "Created document with file upload",
    "timestamp": "2026-04-14T14:48:27.884Z"
  },
  {
    "id": "AUDF920DE7B",
    "action": "document.sign",
    "entityType": "document",
    "entityId": "DOC4041BA18",
    "entityName": "Proposal",
    "userId": "u001",
    "userName": "Ahmed Al-Rashidi",
    "details": "Applied signature",
    "timestamp": "2026-04-15T15:49:37.492Z"
  },
  {
    "id": "AUDC36AF007",
    "action": "document.sign",
    "entityType": "document",
    "entityId": "DOC604A5DD0",
    "entityName": "Proposal",
    "userId": "u001",
    "userName": "Ahmed Al-Rashidi",
    "details": "Applied signature",
    "timestamp": "2026-04-15T16:02:03.009Z"
  },
  {
    "id": "AUD8B2EF8C5",
    "action": "document.sign",
    "entityType": "document",
    "entityId": "DOC604A5DD0",
    "entityName": "Proposal",
    "userId": "u001",
    "userName": "Ahmed Al-Rashidi",
    "details": "Applied signature",
    "timestamp": "2026-04-15T16:02:18.065Z"
  },
  {
    "id": "AUD0524B34C",
    "action": "document.upload",
    "entityType": "document",
    "entityId": "DOC46E279DD",
    "entityName": "Alpha Proposal",
    "userId": "u001",
    "userName": "Ahmed Al-Rashidi",
    "details": "Created document with file upload",
    "timestamp": "2026-04-15T19:33:54.095Z"
  },
  {
    "id": "AUD950C4C15",
    "action": "document.sign",
    "entityType": "document",
    "entityId": "DOC46E279DD",
    "entityName": "Alpha Proposal",
    "userId": "u001",
    "userName": "Ahmed Al-Rashidi",
    "details": "Applied signature",
    "timestamp": "2026-04-15T19:34:24.581Z"
  },
  {
    "id": "AUD58B790F3",
    "action": "document.sign",
    "entityType": "document",
    "entityId": "DOC46E279DD",
    "entityName": "Alpha Proposal",
    "userId": "u001",
    "userName": "Ahmed Al-Rashidi",
    "details": "Applied signature",
    "timestamp": "2026-04-15T19:38:30.388Z"
  },
  {
    "id": "AUD8D14CE03",
    "action": "document.sign",
    "entityType": "document",
    "entityId": "DOC46E279DD",
    "entityName": "Alpha Proposal",
    "userId": "u001",
    "userName": "Ahmed Al-Rashidi",
    "details": "Applied signature",
    "timestamp": "2026-04-15T19:38:48.395Z"
  },
  {
    "id": "AUD5A30F009",
    "action": "document.sign",
    "entityType": "document",
    "entityId": "DOC46E279DD",
    "entityName": "Alpha Proposal",
    "userId": "u001",
    "userName": "Ahmed Al-Rashidi",
    "details": "Applied signature",
    "timestamp": "2026-04-15T19:45:25.659Z"
  },
  {
    "id": "AUD0A822B58",
    "action": "document.sign",
    "entityType": "document",
    "entityId": "DOC46E279DD",
    "entityName": "Alpha Proposal",
    "userId": "u001",
    "userName": "Ahmed Al-Rashidi",
    "details": "Applied signature",
    "timestamp": "2026-04-15T19:53:19.281Z"
  },
  {
    "id": "AUD1E304A5A",
    "action": "document.sign",
    "entityType": "document",
    "entityId": "DOC46E279DD",
    "entityName": "Alpha Proposal",
    "userId": "u001",
    "userName": "Ahmed Al-Rashidi",
    "details": "Applied signature",
    "timestamp": "2026-04-15T20:07:24.430Z"
  },
  {
    "id": "AUD7BA4D4C1",
    "action": "document.sign",
    "entityType": "document",
    "entityId": "DOC46E279DD",
    "entityName": "Alpha Proposal",
    "userId": "u001",
    "userName": "Ahmed Al-Rashidi",
    "details": "Applied signature",
    "timestamp": "2026-04-15T20:08:56.227Z"
  },
  {
    "id": "AUD86822596",
    "action": "document.sign",
    "entityType": "document",
    "entityId": "DOC46E279DD",
    "entityName": "Alpha Proposal",
    "userId": "u001",
    "userName": "Ahmed Al-Rashidi",
    "details": "Applied signature",
    "timestamp": "2026-04-15T20:09:14.342Z"
  },
  {
    "id": "AUD0CB0440A",
    "action": "document.sign",
    "entityType": "document",
    "entityId": "DOC46E279DD",
    "entityName": "Alpha Proposal",
    "userId": "u001",
    "userName": "Ahmed Al-Rashidi",
    "details": "Applied signature",
    "timestamp": "2026-04-15T20:09:41.064Z"
  },
  {
    "id": "AUD26A657C2",
    "action": "document.sign",
    "entityType": "document",
    "entityId": "DOC46E279DD",
    "entityName": "Alpha Proposal",
    "userId": "u001",
    "userName": "Ahmed Al-Rashidi",
    "details": "Applied signature",
    "timestamp": "2026-04-15T20:11:02.825Z"
  },
  {
    "id": "AUD3EB8AA3A",
    "action": "document.lock",
    "entityType": "document",
    "entityId": "DOC46E279DD",
    "entityName": "Alpha Proposal",
    "userId": "u001",
    "userName": "Ahmed Al-Rashidi",
    "details": "Locked document",
    "timestamp": "2026-04-15T20:12:33.166Z"
  },
  {
    "id": "AUD0A788E88",
    "action": "document.unlock",
    "entityType": "document",
    "entityId": "DOC46E279DD",
    "entityName": "Alpha Proposal",
    "userId": "u001",
    "userName": "Ahmed Al-Rashidi",
    "details": "Unlocked document",
    "timestamp": "2026-04-15T20:12:34.249Z"
  },
  {
    "id": "AUDE278B139",
    "action": "document.version",
    "entityType": "document",
    "entityId": "DOC46E279DD",
    "entityName": "Alpha Proposal",
    "userId": "u001",
    "userName": "Ahmed Al-Rashidi",
    "details": "Uploaded version 2",
    "timestamp": "2026-04-15T20:12:51.508Z"
  },
  {
    "id": "AUD853FEDB0",
    "action": "document.sign",
    "entityType": "document",
    "entityId": "DOC604A5DD0",
    "entityName": "Proposal",
    "userId": "u001",
    "userName": "Ahmed Al-Rashidi",
    "details": "Applied signature",
    "timestamp": "2026-04-15T20:22:49.667Z"
  },
  {
    "id": "AUD038B18FA",
    "action": "document.sign",
    "entityType": "document",
    "entityId": "DOC604A5DD0",
    "entityName": "Proposal",
    "userId": "u001",
    "userName": "Ahmed Al-Rashidi",
    "details": "Applied signature",
    "timestamp": "2026-04-15T20:32:09.613Z"
  },
  {
    "id": "AUDA3D32B06",
    "action": "document.annotate",
    "entityType": "document",
    "entityId": "DOC4041BA18",
    "entityName": "Proposal",
    "userId": "u001",
    "userName": "Ahmed Al-Rashidi",
    "details": "Added annotation: \"jknelkfnskfndsf\"",
    "timestamp": "2026-04-15T20:53:53.106Z"
  },
  {
    "id": "AUD181DF95E",
    "action": "document.annotate",
    "entityType": "document",
    "entityId": "DOC4041BA18",
    "entityName": "Proposal",
    "userId": "u001",
    "userName": "Ahmed Al-Rashidi",
    "details": "Added annotation: \"ksldnfkjsdnfksdnf\"",
    "timestamp": "2026-04-15T20:54:06.818Z"
  },
  {
    "id": "AUD9270477E",
    "action": "document.lock",
    "entityType": "document",
    "entityId": "DOC604A5DD0",
    "entityName": "Proposal",
    "userId": "u001",
    "userName": "Ahmed Al-Rashidi",
    "details": "Locked document",
    "timestamp": "2026-04-15T20:55:04.806Z"
  },
  {
    "id": "AUD8D62DCD4",
    "action": "document.sign",
    "entityType": "document",
    "entityId": "DOC604A5DD0",
    "entityName": "Proposal",
    "userId": "u001",
    "userName": "Ahmed Al-Rashidi",
    "details": "Applied signature",
    "timestamp": "2026-04-15T20:55:17.134Z"
  },
  {
    "id": "AUD320B6A4C",
    "action": "document.unlock",
    "entityType": "document",
    "entityId": "DOC604A5DD0",
    "entityName": "Proposal",
    "userId": "u001",
    "userName": "Ahmed Al-Rashidi",
    "details": "Unlocked document",
    "timestamp": "2026-04-15T20:55:20.794Z"
  },
  {
    "id": "AUDFE6789B2",
    "action": "document.lock",
    "entityType": "document",
    "entityId": "DOC604A5DD0",
    "entityName": "Proposal",
    "userId": "u001",
    "userName": "Ahmed Al-Rashidi",
    "details": "Locked document",
    "timestamp": "2026-04-15T20:55:25.793Z"
  },
  {
    "id": "AUDF2162E5F",
    "action": "document.unlock",
    "entityType": "document",
    "entityId": "DOC604A5DD0",
    "entityName": "Proposal",
    "userId": "u001",
    "userName": "Ahmed Al-Rashidi",
    "details": "Unlocked document",
    "timestamp": "2026-04-15T21:04:09.014Z"
  },
  {
    "id": "AUDEEFCE663",
    "action": "document.lock",
    "entityType": "document",
    "entityId": "DOC604A5DD0",
    "entityName": "Proposal",
    "userId": "u001",
    "userName": "Ahmed Al-Rashidi",
    "details": "Locked document",
    "timestamp": "2026-04-15T21:04:09.632Z"
  },
  {
    "id": "AUDC61EC6C2",
    "action": "document.unlock",
    "entityType": "document",
    "entityId": "DOC604A5DD0",
    "entityName": "Proposal",
    "userId": "u001",
    "userName": "Ahmed Al-Rashidi",
    "details": "Unlocked document",
    "timestamp": "2026-04-15T21:05:52.666Z"
  },
  {
    "id": "AUD2066DE6D",
    "action": "document.version",
    "entityType": "document",
    "entityId": "DOC604A5DD0",
    "entityName": "Proposal",
    "userId": "u003",
    "userName": "Fatima Al-Zahra",
    "details": "Uploaded version 2",
    "timestamp": "2026-04-15T21:12:57.961Z"
  },
  {
    "id": "AUDBE415C24",
    "action": "document.version",
    "entityType": "document",
    "entityId": "DOC604A5DD0",
    "entityName": "Proposal",
    "userId": "u003",
    "userName": "Fatima Al-Zahra",
    "details": "Uploaded version 3 (pending approval)",
    "timestamp": "2026-04-15T21:15:19.685Z"
  },
  {
    "id": "AUDDBCFD7CD",
    "action": "document.lock",
    "entityType": "document",
    "entityId": "DOC4041BA18",
    "entityName": "Proposal",
    "userId": "u003",
    "userName": "Fatima Al-Zahra",
    "details": "Locked document",
    "timestamp": "2026-04-15T21:19:12.100Z"
  },
  {
    "id": "AUD78FE2C7E",
    "action": "document.unlock",
    "entityType": "document",
    "entityId": "DOC4041BA18",
    "entityName": "Proposal",
    "userId": "u003",
    "userName": "Fatima Al-Zahra",
    "details": "Unlocked document",
    "timestamp": "2026-04-15T21:19:20.137Z"
  },
  {
    "id": "AUD616DCE07",
    "action": "document.version.rejected",
    "entityType": "document",
    "entityId": "DOC604A5DD0",
    "entityName": "Proposal",
    "userId": "u001",
    "userName": "Ahmed Al-Rashidi",
    "details": "Rejected version 3",
    "timestamp": "2026-04-15T21:33:47.762Z"
  },
  {
    "id": "AUD09E27CEB",
    "action": "document.version",
    "entityType": "document",
    "entityId": "DOC604A5DD0",
    "entityName": "Proposal",
    "userId": "u003",
    "userName": "Fatima Al-Zahra",
    "details": "Uploaded version 3 (pending approval)",
    "timestamp": "2026-04-15T21:34:23.138Z"
  },
  {
    "id": "AUD55B4FE8F",
    "action": "document.version.approved",
    "entityType": "document",
    "entityId": "DOC604A5DD0",
    "entityName": "Proposal",
    "userId": "u001",
    "userName": "Ahmed Al-Rashidi",
    "details": "Approved version 3",
    "timestamp": "2026-04-15T21:34:32.724Z"
  },
  {
    "id": "AUD353889B0",
    "action": "document.sign",
    "entityType": "document",
    "entityId": "DOC604A5DD0",
    "entityName": "Proposal",
    "userId": "u004",
    "userName": "Sara Hassan",
    "details": "Applied signature",
    "timestamp": "2026-04-17T10:59:30.683Z"
  },
  {
    "id": "AUD5CE9E81B",
    "action": "document.annotate",
    "entityType": "document",
    "entityId": "DOC604A5DD0",
    "entityName": "Proposal",
    "userId": "u004",
    "userName": "Sara Hassan",
    "details": "Added annotation: \"Hello\"",
    "timestamp": "2026-04-17T10:59:58.230Z"
  },
  {
    "id": "AUDD0A54A9A",
    "action": "document.version.approved",
    "entityType": "document",
    "entityId": "DOC1A2B3C01",
    "entityName": "Q1 2026 Vendor Invoice - Acme Corp",
    "userId": "u001",
    "userName": "Ahmed Al-Rashidi",
    "details": "Approved version 2",
    "timestamp": "2026-04-19T15:06:43.436Z"
  },
  {
    "id": "AUDEC8D2346",
    "action": "document.version.rejected",
    "entityType": "document",
    "entityId": "DOC1A2B3C01",
    "entityName": "Q1 2026 Vendor Invoice - Acme Corp",
    "userId": "u001",
    "userName": "Ahmed Al-Rashidi",
    "details": "Rejected version 3",
    "timestamp": "2026-04-19T15:06:43.608Z"
  },
  {
    "id": "AUD75F8B54C",
    "action": "document.sign",
    "entityType": "document",
    "entityId": "DOC604A5DD0",
    "entityName": "Proposal",
    "userId": "u001",
    "userName": "Ahmed Al-Rashidi",
    "details": "Applied signature",
    "timestamp": "2026-04-19T15:27:42.892Z"
  },
  {
    "id": "AUD0F0EE84F",
    "action": "document.annotate",
    "entityType": "document",
    "entityId": "DOC604A5DD0",
    "entityName": "Proposal",
    "userId": "u001",
    "userName": "Ahmed Al-Rashidi",
    "details": "Added annotation: \"7655u7uyu\"",
    "timestamp": "2026-04-19T15:27:52.968Z"
  },
  {
    "id": "AUDCCDDD5CB",
    "action": "document.sign",
    "entityType": "document",
    "entityId": "DOC604A5DD0",
    "entityName": "Proposal",
    "userId": "u001",
    "userName": "Ahmed Al-Rashidi",
    "details": "Applied signature",
    "timestamp": "2026-04-19T15:28:26.592Z"
  }
]